{
  "country": {
    "name": "FYR Macedonia",
    "symbol": "flag_fyr_macedonia.png",
    "sid": "fyr_macedonia",
    "rating": "5",
    "leagues": {
      "league": [
        "fyr_macedonia1",
        "fyr_macedonia2",
        "fyr_macedonia3a",
        "fyr_macedonia3b",
        "fyr_macedonia3c",
        "fyr_macedonia3d",
        "fyr_macedonia3e",
        "fyr_macedonia3f"
      ]
    },
    "cups": {
      "cup": [
        "fyr_macedonia_cup",
        "europe_uefa",
        "europe_champ_league",
        "supercup_europe_uefa",
        "supercup_europe_intercontinental",
        "fyr_macedonia_prom_games1"
      ]
    }
  }
}