{
  "league": {
    "sid": "portugal4b",
    "name": "III Divisão Group B",
    "short_name": "III Div. B",
    "symbol": "flag_portugal.png",
    "first_week": "8",
    "week_gap": "1",
    "break": "7",
    "average_talent": "5900",
    "yellow_red": "5",
    "names_file": "portugal",
    "layer": "4",
    "prom_rel": {
      "prom_rel_element": {
        "rank_start": "1",
        "rank_end": "1",
        "dest_sid": "portugal3a portugal3b portugal3c portugal3d",
        "prom_rel_type": "promotion"
      }
    },
    "teams": {
      "team": [
        {
          "team_name": "Coimbroes"
        },
        {
          "team_name": "Vila Mea"
        },
        {
          "team_name": "A. Oliveirense"
        },
        {
          "team_name": "Rebordosa"
        },
        {
          "team_name": "Torre de Moncorvo"
        },
        {
          "team_name": "Paredes"
        },
        {
          "team_name": "Oliveira Douro"
        },
        {
          "team_name": "Leca"
        },
        {
          "team_name": "Vila Real"
        },
        {
          "team_name": "Serzedelo"
        },
        {
          "team_name": "Padroense"
        },
        {
          "team_name": "Alpendorada"
        },
        {
          "team_name": "Lixa"
        }
      ]
    }
  }
}