{
  "league": {
    "sid": "portugal4a",
    "name": "III Divisão Group A",
    "short_name": "III Div. A",
    "symbol": "flag_portugal.png",
    "first_week": "8",
    "week_gap": "1",
    "break": "7",
    "average_talent": "5900",
    "yellow_red": "5",
    "names_file": "portugal",
    "layer": "4",
    "prom_rel": {
      "prom_rel_element": {
        "rank_start": "1",
        "rank_end": "2",
        "dest_sid": "portugal3a portugal3b portugal3c portugal3d",
        "prom_rel_type": "promotion"
      }
    },
    "teams": {
      "team": [
        {
          "team_name": "Vieira"
        },
        {
          "team_name": "Braganca"
        },
        {
          "team_name": "Limianos"
        },
        {
          "team_name": "Fafe"
        },
        {
          "team_name": "Joane"
        },
        {
          "team_name": "M. de Cavaleiros"
        },
        {
          "team_name": "Merelinense"
        },
        {
          "team_name": "Fao"
        },
        {
          "team_name": "Marinhas"
        },
        {
          "team_name": "Prado"
        },
        {
          "team_name": "Vilaverdense"
        },
        {
          "team_name": "Amares"
        },
        {
          "team_name": "Mondinense"
        },
        {
          "team_name": "Mae de Agua"
        }
      ]
    }
  }
}