{
  "league": {
    "sid": "france2",
    "name": "Ligue 2",
    "short_name": "L2",
    "symbol": "flag_france.png",
    "first_week": "6",
    "week_gap": "1",
    "break": "4",
    "average_talent": "6300",
    "names_file": "france",
    "yellow_red": "5",
    "prom_rel": {
      "prom_rel_element": [
        {
          "rank_start": "1",
          "rank_end": "3",
          "dest_sid": "france1",
          "prom_rel_type": "promotion"
        },
        {
          "rank_start": "18",
          "rank_end": "20",
          "dest_sid": "france3",
          "prom_rel_type": "relegation"
        }
      ]
    },
    "teams": {
      "team": [
        {
          "team_name": "Ajaccio"
        },
        {
          "team_name": "Amiens"
        },
        {
          "team_name": "Angers"
        },
        {
          "team_name": "Bastia"
        },
        {
          "team_name": "Boulogne"
        },
        {
          "team_name": "Brest"
        },
        {
          "team_name": "Châteauroux"
        },
        {
          "team_name": "Clermont"
        },
        {
          "team_name": "Dijon"
        },
        {
          "team_name": "Guingamp"
        },
        {
          "team_name": "Lens"
        },
        {
          "team_name": "Metz"
        },
        {
          "team_name": "Montpellier"
        },
        {
          "team_name": "Nîmes"
        },
        {
          "team_name": "Reims"
        },
        {
          "team_name": "Sedan"
        },
        {
          "team_name": "Strasbourg"
        },
        {
          "team_name": "Tours"
        },
        {
          "team_name": "Troyes"
        },
        {
          "team_name": "Vannes"
        }
      ]
    }
  }
}