{
  "league": {
    "sid": "saudi_arabia2",
    "layer": "2",
    "name": "Saudi First Division",
    "short_name": "First Division",
    "symbol": "flag_saudi_arabia.png",
    "first_week": "7",
    "week_gap": "1",
    "average_talent": "6800",
    "yellow_red": "3",
    "names_file": "general",
    "prom_rel": {
      "prom_rel_element": {
        "rank_start": "1",
        "rank_end": "2",
        "dest_sid": "saudi_arabia1",
        "prom_rel_type": "promotion"
      }
    },
    "teams": {
      "team": [
        {
          "team_name": "Al-Faisaly",
          "team_average_talent": "6800"
        },
        {
          "team_name": "Khaleej Club",
          "team_average_talent": "6800"
        },
        {
          "team_name": "Dhamk",
          "team_average_talent": "6800"
        },
        {
          "team_name": "Hajer",
          "team_average_talent": "6800"
        },
        {
          "team_name": "Al-Faihaa",
          "team_average_talent": "6800"
        },
        {
          "team_name": "Al-Taawon",
          "team_average_talent": "6800"
        },
        {
          "team_name": "Al-Fateh",
          "team_average_talent": "6800"
        },
        {
          "team_name": "Al-Riyadh",
          "team_average_talent": "6800"
        },
        {
          "team_name": "Al-Ansar",
          "team_average_talent": "6800"
        },
        {
          "team_name": "Al-Ta'ee",
          "team_average_talent": "6800"
        },
        {
          "team_name": "Sdoos Club",
          "team_average_talent": "6800"
        },
        {
          "team_name": "Al-Jabalain",
          "team_average_talent": "6800"
        },
        {
          "team_name": "Al-Qadisiya",
          "team_average_talent": "6800"
        },
        {
          "team_name": "Ohud",
          "team_average_talent": "6800"
        }
      ]
    }
  }
}