{
  "cup": {
    "name": "Turkish Super Cup",
    "short_name": "Super Cup",
    "symbol": "flag_turkey.png",
    "sid": "turkey_supercup",
    "last_week": "7",
    "property": "national",
    "group": "174",
    "cup_rounds": {
      "cup_round": {
        "home_away": "0",
        "neutral": "1",
        "choose_teams": {
          "choose_team": [
            {
              "choose_team_sid": "turkey_kupasi",
              "number_of_teams": "1",
              "start_idx": "1",
              "end_idx": "1"
            },
            {
              "choose_team_sid": "turkey1",
              "number_of_teams": "1",
              "start_idx": "1",
              "end_idx": "2"
            }
          ]
        }
      }
    }
  }
}