{
  "cup": {
    "name": "Copa América",
    "short_name": "Copa América",
    "sid": "copa_america",
    "symbol": "wc_samerica.png",
    "yellow_red": "2",
    "last_week": "13",
    "add_week": "7",
    "week_gap": "1",
    "property": "international",
    "cup_rounds": {
      "cup_round": [
        {
          "number_of_groups": "3",
          "number_of_advance": "2",
          "number_of_best_advance": "2",
          "new_teams": "12",
          "randomise_teams": "1",
          "home_away": "0",
          "neutral": "1",
          "choose_teams": {
            "choose_team": [
              {
                "choose_team_sid": "conmebol"
              },
              {
                "choose_team_sid": "gold_cup",
                "number_of_teams": "1",
                "start_idx": "2",
                "end_idx": "2"
              },
              {
                "choose_team_sid": "gold_cup_34",
                "number_of_teams": "1",
                "start_idx": "1",
                "end_idx": "1"
              }
            ]
          }
        },
        {
          "home_away": "0",
          "neutral": "1"
        },
        {
          "home_away": "0",
          "neutral": "1"
        },
        {
          "home_away": "0",
          "neutral": "1"
        }
      ]
    }
  }
}