{
  "cup": {
    "name": "Torneo Argentino B",
    "short_name": "Argentino B",
    "symbol": "flag_argentina.png",
    "sid": "argentino_b_final",
    "add_week": "44",
    "last_week": "46",
    "property": [
      "promotion",
      "national",
      "highlight2"
    ],
    "week_gap": "1",
    "cup_rounds": {
      "cup_round": [
        {
          "round_name": "Ascenso",
          "choose_teams": {
            "choose_team": {
              "choose_team_sid": "argentino_b_fase2",
              "number_of_teams": "4",
              "start_idx": "1",
              "end_idx": "4"
            }
          }
        },
        ""
      ]
    }
  }
}